ufcc/__init__.py
ufcc/_version.py
ufcc/contacts.py
ufcc/interactive_sel.py
ufcc/sampledata.py
ufcc/ufcc.py
ufcc/data/README.md
ufcc/data/coordinates.gro
ufcc/data/trajectory.xtc
ufcc/server/app.tpl
ufcc/server/get_json.py
ufcc/server/girk.json
ufcc/server/home.tpl
ufcc/server/index.html
ufcc/server/server.py
ufcc/server/static/js/app.js
ufcc/server/static/js/mol.js
ufcc/tests/__init__.py
ufcc/tests/test_ufcc.py
ufcc-0.0.7.data/scripts/ufcc
ufcc-0.0.7.dist-info/LICENSE
ufcc-0.0.7.dist-info/METADATA
ufcc-0.0.7.dist-info/WHEEL
ufcc-0.0.7.dist-info/top_level.txt
ufcc-0.0.7.dist-info/RECORD
