Metadata-Version: 2.1
Name: ufcc
Version: 0.0.7
Summary: Ultra-Fast Contacts Calculation.
Home-page: https://github.com/ProLint/ufcc
Author: Daniel P. Ramirez & Besian I. Sejdiu
Author-email: daniel.ramirezecheme@ucalgary.ca
License: MIT
Platform: Linux
Platform: Mac OS-X
Platform: Windows
Requires-Python: >=3.8
License-File: LICENSE
Requires-Dist: mdanalysis
Requires-Dist: bottle
